{
  "last_update": "2026-06-14 03:58:40",
  "last_step": "pre_deploy",
  "current_stats": {
    "total_etfs": 1507,
    "has_price": 1466,
    "has_return": 1507,
    "has_sharpe": 1426,
    "has_holdings": 1448,
    "has_issuer": 1504,
    "metrics_count": 1466,
    "yingmi_count": 0,
    "history_count": 1480
  },
  "version_history": [
    {
      "date": "2026-06-11",
      "step": "enrich",
      "stats": {
        "total_etfs": 1500,
        "has_price": 1466,
        "has_return": 1500,
        "has_sharpe": 1425,
        "has_holdings": 1433,
        "has_issuer": 1497,
        "metrics_count": 1466,
        "yingmi_count": 0,
        "history_count": 1480
      }
    },
    {
      "date": "2026-06-11",
      "step": "calc",
      "stats": {
        "total_etfs": 1500,
        "has_price": 1466,
        "has_return": 1500,
        "has_sharpe": 1425,
        "has_holdings": 1433,
        "has_issuer": 1497,
        "metrics_count": 1466,
        "yingmi_count": 0,
        "history_count": 1480
      }
    },
    {
      "date": "2026-06-11",
      "step": "build",
      "stats": {
        "total_etfs": 1503,
        "has_price": 1466,
        "has_return": 1503,
        "has_sharpe": 1421,
        "has_holdings": 1441,
        "has_issuer": 1500,
        "metrics_count": 1466,
        "yingmi_count": 0,
        "history_count": 1480
      }
    },
    {
      "date": "2026-06-11",
      "step": "pre_deploy",
      "stats": {
        "total_etfs": 1503,
        "has_price": 1466,
        "has_return": 1503,
        "has_sharpe": 1421,
        "has_holdings": 1441,
        "has_issuer": 1500,
        "metrics_count": 1466,
        "yingmi_count": 0,
        "history_count": 1480
      }
    },
    {
      "date": "2026-06-11",
      "step": "deploy",
      "stats": {
        "total_etfs": 1503,
        "has_price": 1466,
        "has_return": 1503,
        "has_sharpe": 1421,
        "has_holdings": 1441,
        "has_issuer": 1500,
        "metrics_count": 1466,
        "yingmi_count": 0,
        "history_count": 1480
      }
    },
    {
      "date": "2026-06-11",
      "step": "pre_deploy",
      "stats": {
        "total_etfs": 1503,
        "has_price": 1466,
        "has_return": 1503,
        "has_sharpe": 1421,
        "has_holdings": 1441,
        "has_issuer": 1500,
        "metrics_count": 1466,
        "yingmi_count": 0,
        "history_count": 1480
      }
    },
    {
      "date": "2026-06-11",
      "step": "deploy",
      "stats": {
        "total_etfs": 1503,
        "has_price": 1466,
        "has_return": 1503,
        "has_sharpe": 1421,
        "has_holdings": 1441,
        "has_issuer": 1500,
        "metrics_count": 1466,
        "yingmi_count": 0,
        "history_count": 1480
      }
    },
    {
      "date": "2026-06-11",
      "step": "pre_deploy",
      "stats": {
        "total_etfs": 1503,
        "has_price": 1466,
        "has_return": 1503,
        "has_sharpe": 1425,
        "has_holdings": 1441,
        "has_issuer": 1500,
        "metrics_count": 1466,
        "yingmi_count": 0,
        "history_count": 1480
      }
    },
    {
      "date": "2026-06-11",
      "step": "deploy",
      "stats": {
        "total_etfs": 1503,
        "has_price": 1466,
        "has_return": 1503,
        "has_sharpe": 1425,
        "has_holdings": 1441,
        "has_issuer": 1500,
        "metrics_count": 1466,
        "yingmi_count": 0,
        "history_count": 1480
      }
    },
    {
      "date": "2026-06-13",
      "step": "sync",
      "stats": {
        "total_etfs": 1503,
        "has_price": 1466,
        "has_return": 1503,
        "has_sharpe": 1426,
        "has_holdings": 1441,
        "has_issuer": 1500,
        "metrics_count": 1466,
        "yingmi_count": 0,
        "history_count": 1480
      }
    },
    {
      "date": "2026-06-13",
      "step": "enrich",
      "stats": {
        "total_etfs": 1503,
        "has_price": 1466,
        "has_return": 1503,
        "has_sharpe": 1426,
        "has_holdings": 1441,
        "has_issuer": 1500,
        "metrics_count": 1466,
        "yingmi_count": 0,
        "history_count": 1480
      }
    },
    {
      "date": "2026-06-13",
      "step": "calc",
      "stats": {
        "total_etfs": 1503,
        "has_price": 1466,
        "has_return": 1503,
        "has_sharpe": 1426,
        "has_holdings": 1441,
        "has_issuer": 1500,
        "metrics_count": 1466,
        "yingmi_count": 0,
        "history_count": 1480
      }
    },
    {
      "date": "2026-06-13",
      "step": "build",
      "stats": {
        "total_etfs": 1507,
        "has_price": 1466,
        "has_return": 1507,
        "has_sharpe": 1421,
        "has_holdings": 1444,
        "has_issuer": 1504,
        "metrics_count": 1466,
        "yingmi_count": 0,
        "history_count": 1480
      }
    },
    {
      "date": "2026-06-13",
      "step": "pre_deploy",
      "stats": {
        "total_etfs": 1507,
        "has_price": 1466,
        "has_return": 1507,
        "has_sharpe": 1421,
        "has_holdings": 1444,
        "has_issuer": 1504,
        "metrics_count": 1466,
        "yingmi_count": 0,
        "history_count": 1480
      }
    },
    {
      "date": "2026-06-13",
      "step": "deploy",
      "stats": {
        "total_etfs": 1507,
        "has_price": 1466,
        "has_return": 1507,
        "has_sharpe": 1421,
        "has_holdings": 1444,
        "has_issuer": 1504,
        "metrics_count": 1466,
        "yingmi_count": 0,
        "history_count": 1480
      }
    },
    {
      "date": "2026-06-13",
      "step": "pre_deploy",
      "stats": {
        "total_etfs": 1507,
        "has_price": 1466,
        "has_return": 1507,
        "has_sharpe": 1421,
        "has_holdings": 1444,
        "has_issuer": 1504,
        "metrics_count": 1466,
        "yingmi_count": 0,
        "history_count": 1480
      }
    },
    {
      "date": "2026-06-13",
      "step": "deploy",
      "stats": {
        "total_etfs": 1507,
        "has_price": 1466,
        "has_return": 1507,
        "has_sharpe": 1421,
        "has_holdings": 1444,
        "has_issuer": 1504,
        "metrics_count": 1466,
        "yingmi_count": 0,
        "history_count": 1480
      }
    },
    {
      "date": "2026-06-13",
      "step": "pre_deploy",
      "stats": {
        "total_etfs": 1507,
        "has_price": 1466,
        "has_return": 1507,
        "has_sharpe": 1426,
        "has_holdings": 1444,
        "has_issuer": 1504,
        "metrics_count": 1466,
        "yingmi_count": 0,
        "history_count": 1480
      }
    },
    {
      "date": "2026-06-13",
      "step": "deploy",
      "stats": {
        "total_etfs": 1507,
        "has_price": 1466,
        "has_return": 1507,
        "has_sharpe": 1426,
        "has_holdings": 1444,
        "has_issuer": 1504,
        "metrics_count": 1466,
        "yingmi_count": 0,
        "history_count": 1480
      }
    },
    {
      "date": "2026-06-14",
      "step": "sync",
      "stats": {
        "total_etfs": 1507,
        "has_price": 1466,
        "has_return": 1507,
        "has_sharpe": 1426,
        "has_holdings": 1444,
        "has_issuer": 1504,
        "metrics_count": 1466,
        "yingmi_count": 0,
        "history_count": 1480
      }
    },
    {
      "date": "2026-06-14",
      "step": "enrich",
      "stats": {
        "total_etfs": 1507,
        "has_price": 1466,
        "has_return": 1507,
        "has_sharpe": 1426,
        "has_holdings": 1444,
        "has_issuer": 1504,
        "metrics_count": 1466,
        "yingmi_count": 0,
        "history_count": 1480
      }
    },
    {
      "date": "2026-06-14",
      "step": "sync",
      "stats": {
        "total_etfs": 1507,
        "has_price": 1466,
        "has_return": 1507,
        "has_sharpe": 1426,
        "has_holdings": 1444,
        "has_issuer": 1504,
        "metrics_count": 1466,
        "yingmi_count": 0,
        "history_count": 1480
      }
    },
    {
      "date": "2026-06-14",
      "step": "enrich",
      "stats": {
        "total_etfs": 1507,
        "has_price": 1466,
        "has_return": 1507,
        "has_sharpe": 1426,
        "has_holdings": 1444,
        "has_issuer": 1504,
        "metrics_count": 1466,
        "yingmi_count": 0,
        "history_count": 1480
      }
    },
    {
      "date": "2026-06-14",
      "step": "calc",
      "stats": {
        "total_etfs": 1507,
        "has_price": 1466,
        "has_return": 1507,
        "has_sharpe": 1426,
        "has_holdings": 1444,
        "has_issuer": 1504,
        "metrics_count": 1466,
        "yingmi_count": 0,
        "history_count": 1480
      }
    },
    {
      "date": "2026-06-14",
      "step": "build",
      "stats": {
        "total_etfs": 1507,
        "has_price": 1466,
        "has_return": 1507,
        "has_sharpe": 1421,
        "has_holdings": 1448,
        "has_issuer": 1504,
        "metrics_count": 1466,
        "yingmi_count": 0,
        "history_count": 1480
      }
    },
    {
      "date": "2026-06-14",
      "step": "pre_deploy",
      "stats": {
        "total_etfs": 1507,
        "has_price": 1466,
        "has_return": 1507,
        "has_sharpe": 1421,
        "has_holdings": 1448,
        "has_issuer": 1504,
        "metrics_count": 1466,
        "yingmi_count": 0,
        "history_count": 1480
      }
    },
    {
      "date": "2026-06-14",
      "step": "deploy",
      "stats": {
        "total_etfs": 1507,
        "has_price": 1466,
        "has_return": 1507,
        "has_sharpe": 1421,
        "has_holdings": 1448,
        "has_issuer": 1504,
        "metrics_count": 1466,
        "yingmi_count": 0,
        "history_count": 1480
      }
    },
    {
      "date": "2026-06-14",
      "step": "pre_deploy",
      "stats": {
        "total_etfs": 1507,
        "has_price": 1466,
        "has_return": 1507,
        "has_sharpe": 1421,
        "has_holdings": 1448,
        "has_issuer": 1504,
        "metrics_count": 1466,
        "yingmi_count": 0,
        "history_count": 1480
      }
    },
    {
      "date": "2026-06-14",
      "step": "deploy",
      "stats": {
        "total_etfs": 1507,
        "has_price": 1466,
        "has_return": 1507,
        "has_sharpe": 1421,
        "has_holdings": 1448,
        "has_issuer": 1504,
        "metrics_count": 1466,
        "yingmi_count": 0,
        "history_count": 1480
      }
    },
    {
      "date": "2026-06-14",
      "step": "pre_deploy",
      "stats": {
        "total_etfs": 1507,
        "has_price": 1466,
        "has_return": 1507,
        "has_sharpe": 1426,
        "has_holdings": 1448,
        "has_issuer": 1504,
        "metrics_count": 1466,
        "yingmi_count": 0,
        "history_count": 1480
      }
    }
  ]
}